aria2a-0.1.0.dist-info/METADATA
aria2a-0.1.0.dist-info/WHEEL
aria2a-0.1.0.dist-info/licenses/LICENSE
aria2a/__init__.py
aria2a/aria2a.cp313-win_amd64.pyd
aria2a-0.1.0.dist-info/RECORD
