Metadata-Version: 2.4
Name: aria2a
Version: 0.1.0
Classifier: Development Status :: 4 - Beta
Classifier: Intended Audience :: Developers
Classifier: License :: OSI Approved :: MIT License
Classifier: Programming Language :: Rust
Classifier: Programming Language :: Python :: 3
Classifier: Programming Language :: Python :: 3.8
Classifier: Programming Language :: Python :: 3.9
Classifier: Programming Language :: Python :: 3.10
Classifier: Programming Language :: Python :: 3.11
Classifier: Programming Language :: Python :: 3.12
Classifier: Programming Language :: Python :: 3.13
Classifier: Topic :: Internet :: WWW/HTTP
Classifier: Topic :: System :: Archiving :: Compression
Classifier: Topic :: Utilities
License-File: LICENSE
Summary: aria2a is a high-performance, self-contained Python library for aria2 download manager with embedded aria2c binary and comprehensive security layers.
Keywords: aria2,download,rpc,json-rpc,progress-bar
Author-email: ahmetpia <ahmt_ergn@outlook.com>
License: MIT
Requires-Python: >=3.8
Project-URL: Homepage, https://github.com/ahmetpia/aria2a
Project-URL: Repository, https://github.com/ahmetpia/aria2a.git
Project-URL: Issues, https://github.com/ahmetpia/aria2a/issues
